batserve/__init__.py
batserve/__main__.py
batserve/batserve.py
batServe-1.0rc7.dist-info/METADATA
batServe-1.0rc7.dist-info/WHEEL
batServe-1.0rc7.dist-info/entry_points.txt
batServe-1.0rc7.dist-info/top_level.txt
batServe-1.0rc7.dist-info/RECORD
