Metadata-Version: 2.1
Name: batServe
Version: 1.0rc7
Summary: Simple file server and reverse proxy | part of batBelt
Home-page: https://github.com/notAI-tech/batBelt
Author: BEDAPUDI PRANEETH
Author-email: praneeth@bpraneeth.com
License: MIT
Platform: UNKNOWN
Classifier: License :: OSI Approved :: MIT License
Classifier: Programming Language :: Python
Classifier: Programming Language :: Python :: 3
Classifier: Programming Language :: Python :: 3.6
Classifier: Programming Language :: Python :: Implementation :: CPython
Requires-Python: >=3.6.0
Requires-Dist: psutil
Requires-Dist: falcon
Requires-Dist: gevent
Requires-Dist: gunicorn
Requires-Dist: rich
Requires-Dist: falcon-auth2
